easierAPI/__init__.py
easierAPI/easyapi.py
easierAPI-0.0.1.dist-info/LICENCE
easierAPI-0.0.1.dist-info/METADATA
easierAPI-0.0.1.dist-info/WHEEL
easierAPI-0.0.1.dist-info/top_level.txt
easierAPI-0.0.1.dist-info/RECORD
