Metadata-Version: 2.1
Name: easierAPI
Version: 0.0.1
Summary: An easier way to use a JSON api.
Home-page: https://github.com/mathstar13/easyAPI
Author: greatusername
Author-email: alexander.destefano@gmail.com
License: UNKNOWN
Platform: UNKNOWN
Classifier: Programming Language :: Python :: 3
Classifier: License :: OSI Approved :: MIT License
Classifier: Operating System :: OS Independent
Requires-Python: >=3.1
